wagtail_wordpress_image_importer/__init__.py
wagtail_wordpress_image_importer/apps.py
wagtail_wordpress_image_importer/management/__init__.py
wagtail_wordpress_image_importer/management/commands/__init__.py
wagtail_wordpress_image_importer/management/commands/import_wordpress_images.py
wagtail_wordpress_image_importer-0.1.0.dist-info/LICENSE
wagtail_wordpress_image_importer-0.1.0.dist-info/METADATA
wagtail_wordpress_image_importer-0.1.0.dist-info/WHEEL
wagtail_wordpress_image_importer-0.1.0.dist-info/top_level.txt
wagtail_wordpress_image_importer-0.1.0.dist-info/RECORD
