Metadata-Version: 2.1
Name: wagtail-wordpress-image-importer
Version: 0.1.0
Summary: Import WordPress images into Wagtail
Author: Tom Dyson
License: MIT License
Project-URL: Homepage, https://github.com/tomdyson/wagtail-wordpress-image-importer
Keywords: wagtail,wordpress,images,import
Classifier: Development Status :: 3 - Alpha
Classifier: Environment :: Web Environment
Classifier: Framework :: Django
Classifier: Framework :: Wagtail
Classifier: Intended Audience :: Developers
Classifier: License :: OSI Approved :: MIT License
Classifier: Programming Language :: Python :: 3
Classifier: Programming Language :: Python :: 3.8
Classifier: Programming Language :: Python :: 3.9
Classifier: Programming Language :: Python :: 3.10
Classifier: Programming Language :: Python :: 3.11
Requires-Python: >=3.8
License-File: LICENSE
Requires-Dist: wagtail>=5.0
Requires-Dist: requests>=2.25.0
Requires-Dist: Pillow>=9.0.0
Requires-Dist: tqdm>=4.65.0
